lime_transport_websocket/__init__.py
lime_transport_websocket/websocket_transport.py
lime_transport_websocket-1.0.9.dist-info/METADATA
lime_transport_websocket-1.0.9.dist-info/WHEEL
lime_transport_websocket-1.0.9.dist-info/top_level.txt
lime_transport_websocket-1.0.9.dist-info/RECORD
